neuropsychdata/__init__.py
neuropsychdata/testing.py
tests/__init__.py
tests/test_myfunctions.py
neuropsychdata-0.0.1.dist-info/LICENCE.md
neuropsychdata-0.0.1.dist-info/METADATA
neuropsychdata-0.0.1.dist-info/WHEEL
neuropsychdata-0.0.1.dist-info/top_level.txt
neuropsychdata-0.0.1.dist-info/RECORD
