Metadata-Version: 2.1
Name: neuropsychdata
Version: 0.0.1
Summary: A python library to analyze neuropsychological data
Author: Gustavo Juantorena
License: MIT
License-File: LICENCE.md
